src/__init__.py
src/app.py
src/configuration.py
src/configuration.yaml
src/exceptions.py
src/main.py
src/prompt.py
src/requirements.txt
outerspace_apizr-0.1.3.1.dist-info/METADATA
outerspace_apizr-0.1.3.1.dist-info/WHEEL
outerspace_apizr-0.1.3.1.dist-info/entry_points.txt
outerspace_apizr-0.1.3.1.dist-info/RECORD
