Metadata-Version: 2.1
Name: outerspace-apizr
Version: 0.1.3.1
Summary: Apizr is a dynamic API generator built on top of FastAPI. It analyses your Python codebase, extracts relevant metadata, and automatically generates a FastAPI backend for your application. This simplifies the process of API development, saving time, and reducing the chance of errors.
License: GPL-3.0-or-later
Author: Ludovic FERNANDEZ
Author-email: ludovic.fernandez@alien6.com
Requires-Python: >=3.8,<4.0
Classifier: License :: OSI Approved :: GNU General Public License v3 or later (GPLv3+)
Classifier: Programming Language :: Python :: 3
Classifier: Programming Language :: Python :: 3.8
Classifier: Programming Language :: Python :: 3.9
Classifier: Programming Language :: Python :: 3.10
Classifier: Programming Language :: Python :: 3.11
Requires-Dist: Jinja2 (>=3.1.2,<4.0.0)
Requires-Dist: PyInquirer (>=1.0.3,<2.0.0)
Requires-Dist: PyYAML (>=6.0.1,<7.0.0)
Requires-Dist: black
Requires-Dist: fastapi (>=0.103.0,<0.104.0)
Requires-Dist: ipython
Requires-Dist: nbconvert
Requires-Dist: pipreqs
Requires-Dist: pydantic (>=2.3.0,<3.0.0)
Requires-Dist: python-multipart (>=0.0.6,<0.0.7)
Requires-Dist: uvicorn[standard]
Project-URL: Repository, https://github.com/Alien6-Studio/outerspace-apizr
Project-URL: Website, https://apizr.outerspace.sh
